qoder_mcp_server/__init__.py
qoder_mcp_server/main.py
qoder_mcp_server/tools/__init__.py
qoder_mcp_server/tools/dashscope_tools.py
qoder_mcp_server/tools/pwd.py
qoder_mcp_server-0.1.3.dist-info/METADATA
qoder_mcp_server-0.1.3.dist-info/WHEEL
qoder_mcp_server-0.1.3.dist-info/entry_points.txt
qoder_mcp_server-0.1.3.dist-info/RECORD
