Metadata-Version: 2.4
Name: qoder-mcp-server
Version: 0.1.3
Summary: A custom MCP server for Qoder with file operations and DashScope integration
Project-URL: Repository, https://github.com/caryz/Qoder-test
Author-email: CaryZ <caryz@example.com>
License: MIT
Classifier: Development Status :: 4 - Beta
Classifier: Intended Audience :: Developers
Classifier: Programming Language :: Python
Classifier: Programming Language :: Python :: 3
Classifier: Programming Language :: Python :: 3.10
Classifier: Programming Language :: Python :: 3.11
Classifier: Programming Language :: Python :: 3.12
Classifier: Topic :: Software Development :: Libraries :: Python Modules
Requires-Python: >=3.13
Requires-Dist: httpx>=0.27.0
Requires-Dist: mcp>=1.0.0
